<?xml version="1.0" encoding="utf-8" ?>

<!DOCTYPE class-list[

<!ELEMENT class-list ( java-class* ) >

<!ELEMENT java-class (para*, compare*) >
<!ATTLIST java-class name CDATA #REQUIRED >
<!ATTLIST java-class class CDATA #REQUIRED >
<!ATTLIST java-class service CDATA #IMPLIED >
<!ATTLIST java-class all-match (true|false) #IMPLIED > <!-- default : false -->

<!ELEMENT compare EMPTY >
<!ATTLIST compare field CDATA #REQUIRED >
<!ATTLIST compare result CDATA #IMPLIED >
<!ATTLIST compare method CDATA #REQUIRED >
<!ATTLIST compare value CDATA #REQUIRED >

<!ELEMENT para EMPTY >
<!ATTLIST para name CDATA #REQUIRED >
<!ATTLIST para value CDATA #IMPLIED>
<!ATTLIST para os CDATA #IMPLIED >
<!ATTLIST para descr CDATA #IMPLIED>

]>

<class-list>

<!-- 

	<java-class name="container.temp.1" class="fxms.bas.mo.child.AutoAddChild">

		<para name="moClass" value="DEVICE" />
		<para name="moClass" value="DEVICE" />
		<para name="moName" value="%containerId%.TEMP.1" />
		<para name="moAname" value="%containerId%.TEMP.1" />
		<para name="deviceIdInGw" value="%containerId%.TEMP.1" />
		<para name="gwMoNo" value="%gwMoNo%" />
		<para name="deviceType" value="TEMP" />

		<compare value="24ft-A" field="containerType" method="equals" />

	</java-class>
	
	<java-class name="container.temp.2" class="fxms.bas.mo.child.AutoAddChild">

		<para name="moClass" value="DEVICE" />
		<para name="moName" value="%containerId%.TEMP.2" />
		<para name="moAname" value="%containerId%.TEMP.2" />
		<para name="deviceIdInGw" value="%containerId%.TEMP.2" />
		<para name="gwMoNo" value="%gwMoNo%" />
		<para name="deviceType" value="TEMP" />

		<compare value="24ft-A" field="containerType" method="equals" />

	</java-class>
	
	<java-class name="container.co2.1" class="fxms.bas.mo.child.AutoAddChild">

		<para name="moClass" value="DEVICE" />
		<para name="moName" value="%containerId%.CO2.1" />
		<para name="moAname" value="%containerId%.CO2.1" />
		<para name="deviceIdInGw" value="%containerId%.CO2.1" />
		<para name="gwMoNo" value="%gwMoNo%" />
		<para name="deviceType" value="CO2" />

		<compare value="24ft-A" field="containerType" method="equals" />

	</java-class>
	
	 -->

</class-list>